{
    "UniqueID": "herbs_fungi_bp_herbal_tincture",
    "CardName": {
        "ParentObjectID": "herbs_fungi_bp_herbal_tincture",
        "LocalizationKey": "Herbs_And_Fungi_Bp_HerbalTincture_CardName",
        "DefaultText": "Herbal Tincture"
    },
    "CardDescription": {
        "ParentObjectID": "herbs_fungi_bp_herbal_tincture",
        "LocalizationKey": "Herbs_And_Fungi_Bp_HerbalTincture_CardDescription",
        "DefaultText": "Press 3 dried yarrow into a clay bowl at the oil press to extract a medicinal tincture. A bitter but effective all-purpose remedy."
    },
    "CardType": 7,
    "UnlockConditionsDesc": {
        "ParentObjectID": "herbs_fungi_bp_herbal_tincture",
        "LocalizationKey": "Herbs_And_Fungi_Bp_HerbalTincture_UnlockConditionsDesc",
        "DefaultText": "Unlocked after obtaining Dried Yarrow"
    },
    "BlueprintUnlockTicksCost": 16.0,
    "BuildingStatConditions": [],
    "StartUnlocked": false,
    "CardsOnBoard": [
        {
            "ObjectiveName": "HasYarrowDried",
            "CompletionWeight": 1,
            "Card": {
                "m_FileID": 0,
                "m_PathID": 0
            },
            "Quantity": 1,
            "ConstantlyChecking": false,
            "OnlyInEnvironment": {
                "m_FileID": 0,
                "m_PathID": 0
            },
            "OnlyIfEquipped": false,
            "OnlyInContainer": {
                "Target": {
                    "m_FileID": 0,
                    "m_PathID": 0
                }
            },
            "CardWarpData": "herbs_fungi_yarrow_dried",
            "CardWarpType": 3
        },
        {
            "ObjectiveName": "HasOilPress",
            "CompletionWeight": 1,
            "Card": {
                "m_FileID": 0,
                "m_PathID": 0
            },
            "Quantity": 1,
            "ConstantlyChecking": true,
            "OnlyInEnvironment": {
                "m_FileID": 0,
                "m_PathID": 0
            },
            "OnlyIfEquipped": false,
            "OnlyInContainer": {
                "Target": {
                    "m_FileID": 0,
                    "m_PathID": 0
                }
            },
            "CardWarpData": "herbs_fungi_oil_press",
            "CardWarpType": 3
        }
    ],
    "TagsOnBoard": [],
    "StatValues": [],
    "BlueprintStages": [
        {
            "CannotRevertToThisStage": false,
            "RequiredElements": [
                {
                    "RequiredCard": {
                        "m_FileID": 0,
                        "m_PathID": 0
                    },
                    "RequiredTabGroup": {
                        "m_FileID": 0,
                        "m_PathID": 0
                    },
                    "RequiredQuantity": 3,
                    "DontSpend": false,
                    "RequiredCardWarpData": "herbs_fungi_yarrow_dried",
                    "RequiredCardWarpType": 3
                },
                {
                    "RequiredCard": {
                        "m_FileID": 0,
                        "m_PathID": 0
                    },
                    "RequiredTabGroup": {
                        "m_FileID": 0,
                        "m_PathID": 0
                    },
                    "RequiredQuantity": 1,
                    "DontSpend": false,
                    "RequiredCardWarpData": "a968f3eaffc6b9743b82982b5af2ab8c",
                    "RequiredCardWarpType": 3
                }
            ],
            "StepActionTags": [],
            "StepActionTagsWarpData": [
                "HandAction",
                "CraftAction"
            ],
            "StepActionTagsWarpType": 3
        }
    ],
    "BuildingDaytimeCost": 2,
    "DeconstructDaytimeCost": 1,
    "BlueprintResult": [
        {
            "DroppedCard": {
                "m_FileID": 0,
                "m_PathID": 0
            },
            "Quantity": {
                "x": 1,
                "y": 1
            },
            "DroppedCardWarpData": "herbs_fungi_herbal_tincture",
            "DroppedCardWarpType": 3
        }
    ],
    "BlueprintStatModifications": [],
    "WhenCreatedSoundsWarpData": [
        "Wood"
    ],
    "WhenCreatedSoundsWarpType": 3,
    "BlueprintActionTagsWarpData": [
        "HandAction",
        "CraftAction"
    ],
    "BlueprintActionTagsWarpType": 3,
    "CardImage": {
        "m_FileID": 0,
        "m_PathID": 0
    },
    "CardImageWarpData": "Bowl_Clay",
    "CardImageWarpType": 3,
    "ResearchedNotification": 0
}
